{
  "page": "1",
  "total": "823",
  "records": "15",
  "rows": [{
    "isCheck": false,
    "account": "admin",
    "userName": "系统管理员",
    "userOrgName": "山东省本部信息安全管理部"
  }, {
    "isCheck": false,
    "account": "admin2",
    "userName": "admin2",
    "userOrgName": "山东省本部信息安全管理部"
  }, {
    "isCheck": false,
    "account": "admin3",
    "userName": "admin3",
    "userOrgName": "山东省本部信息安全管理部"
  }, {
    "isCheck": false,
    "account": "aiyan",
    "userName": "艾岩 ",
    "userCode": "32215083",
    "userOrgName": "山东省本部政企客户部"
  }, {
    "isCheck": false,
    "account": "anzhenyu",
    "userName": "安振宇",
    "userCode": "32170145",
    "userOrgName": "山东省本部采购部"
  }, {
    "isCheck": false,
    "account": "baixiaojing",
    "userName": "白晓晶",
    "userCode": "32000209",
    "userOrgName": "山东省本部财务部"
  }, {
    "isCheck": false,
    "account": "baowanchang",
    "userName": "鲍万昌",
    "userCode": "32000285",
    "userOrgName": "山东省本部信息技术部"
  }, {
    "isCheck": false,
    "account": "bianliqun",
    "userName": "边利群",
    "userCode": "32010067",
    "userOrgName": "山东省本部建设部"
  }, {
    "isCheck": false,
    "account": "bijianliang",
    "userName": "毕见良",
    "userCode": "32000024",
    "userOrgName": "山东省本部内审部"
  }, {
    "isCheck": false,
    "account": "bishuwen",
    "userName": "毕舒文 ",
    "userCode": "32200114",
    "userOrgName": "山东省本部政企客户部"
  }, {
    "isCheck": false,
    "account": "bixiaoxia",
    "userName": "毕晓霞",
    "userCode": "32010120",
    "userOrgName": "山东省本部网络部"
  }, {
    "isCheck": false,
    "account": "biyantao",
    "userName": "毕研涛",
    "userCode": "32000359",
    "userOrgName": "山东省本部网络部"
  }, {
    "isCheck": false,
    "account": "biyinglian",
    "userName": "毕映莲",
    "userCode": "32000369",
    "userOrgName": "山东省本部市场经营部"
  }, {
    "isCheck": false,
    "account": "bulu1",
    "userName": "卜璐",
    "userCode": "32160281",
    "userOrgName": "山东省本部财务部"
  }, {
    "isCheck": false,
    "account": "caochengzu",
    "userName": "曹承祖",
    "userCode": "32000073",
    "userOrgName": "山东省本部数字家庭业务运营中心"
  }]
}